setup.cfg
setup.py
spiget/__init__.py
spiget.egg-info/PKG-INFO
spiget.egg-info/SOURCES.txt
spiget.egg-info/dependency_links.txt
spiget.egg-info/requires.txt
spiget.egg-info/top_level.txt