Metadata-Version: 1.1
Name: spiget
Version: 0.1.2
Summary: Spiget.org API Interaction
Home-page: https://github.com/TechnicalBro/spiget
Author: Brandon Curtis
Author-email: freebird.brandon@gmail.com
License: UNKNOWN
Download-URL: https://github.com/TechnicalBro/spiget/tarball/0.1.1
Keywords: spigotmc,spiget,minecraft,bukkit
Platform: UNKNOWN
